smithed/__init__.py
smithed/theming.py
smithed/type.py
smithed/utils.py
smithed/weld/__init__.py
smithed/weld/__main__.py
smithed/weld/errors.py
smithed/weld/merging/__init__.py
smithed/weld/merging/errors.py
smithed/weld/merging/handler.py
smithed/weld/merging/parser.py
smithed/weld/merging/plugin.py
smithed/weld/models/__init__.py
smithed/weld/models/base.py
smithed/weld/models/conditions.py
smithed/weld/models/main.py
smithed/weld/models/priority.py
smithed/weld/models/rules.py
smithed/weld/models/sources.py
smithed/weld/resources/fabric.mod.json.j2
smithed/weld/resources/icon.png
smithed/weld/resources/webapp.yaml
smithed/weld/toolchain/__init__.py
smithed/weld/toolchain/cli.py
smithed/weld/toolchain/helper_plugins.py
smithed/weld/toolchain/main.py
smithed/weld/webapp/__init__.py
smithed/weld/webapp/__main__.py
smithed/weld/webapp/common.py
smithed/weld/webapp/log_helpers.py
smithed/weld/webapp/merging.py
smithed/weld/webapp/models.py
smithed/weld/webapp/preview.py
weld/__init__.py
weld/__main__.py
weld/errors.py
weld/merging/__init__.py
weld/merging/errors.py
weld/merging/handler.py
weld/merging/parser.py
weld/merging/plugin.py
weld/models/__init__.py
weld/models/base.py
weld/models/conditions.py
weld/models/main.py
weld/models/priority.py
weld/models/rules.py
weld/models/sources.py
weld/resources/fabric.mod.json.j2
weld/resources/icon.png
weld/resources/webapp.yaml
weld/toolchain/__init__.py
weld/toolchain/cli.py
weld/toolchain/helper_plugins.py
weld/toolchain/main.py
weld/webapp/__init__.py
weld/webapp/__main__.py
weld/webapp/common.py
weld/webapp/log_helpers.py
weld/webapp/merging.py
weld/webapp/models.py
weld/webapp/preview.py
smithed-0.19.0.dist-info/METADATA
smithed-0.19.0.dist-info/WHEEL
smithed-0.19.0.dist-info/entry_points.txt
smithed-0.19.0.dist-info/licenses/LICENSE
smithed-0.19.0.dist-info/RECORD
