Metadata-Version: 2.1
Name: smithed
Version: 0.19.0
Summary: Smithed's Python client with CLI, weld and more
Author-email: Smithed Team <team@smithed.dev>
License-Expression: MIT
License-File: LICENSE
Requires-Python: >=3.10
Requires-Dist: backports-strenum>=1.2.8
Requires-Dist: beet>=0.100.0
Requires-Dist: mecha>=0.76.2
Requires-Dist: pydantic>=2.5.2
Requires-Dist: rich>=13.6.0
Requires-Dist: tokenstream>=1.7.0
Requires-Dist: typer>=0.9.0
